retro_pytorch/__init__.py
retro_pytorch/data.py
retro_pytorch/optimizer.py
retro_pytorch/retrieval.py
retro_pytorch/retro_pytorch.py
retro_pytorch/training.py
retro_pytorch/utils.py
retro_pytorch-0.3.9.dist-info/LICENSE
retro_pytorch-0.3.9.dist-info/METADATA
retro_pytorch-0.3.9.dist-info/WHEEL
retro_pytorch-0.3.9.dist-info/top_level.txt
retro_pytorch-0.3.9.dist-info/RECORD
