Metadata-Version: 2.1
Name: retro-pytorch
Version: 0.3.9
Summary: RETRO - Retrieval Enhanced Transformer - Pytorch
Home-page: https://github.com/lucidrains/RETRO-pytorch
Author: Phil Wang
Author-email: lucidrains@gmail.com
License: MIT
Keywords: artificial intelligence,deep learning,transformers,attention-mechanism,retrieval
Classifier: Development Status :: 4 - Beta
Classifier: Intended Audience :: Developers
Classifier: Topic :: Scientific/Engineering :: Artificial Intelligence
Classifier: License :: OSI Approved :: MIT License
Classifier: Programming Language :: Python :: 3.6
License-File: LICENSE
Requires-Dist: autofaiss
Requires-Dist: einops >=0.3
Requires-Dist: numpy
Requires-Dist: sentencepiece
Requires-Dist: torch >=1.6
Requires-Dist: tqdm
